LICENSE
README.md
setup.py
smoot/__init__.py
smoot/criterion.py
smoot/montecarlo.py
smoot/smoot.py
smoot/utils.py
smoot/zdt.py
smoot.egg-info/PKG-INFO
smoot.egg-info/SOURCES.txt
smoot.egg-info/dependency_links.txt
smoot.egg-info/requires.txt
smoot.egg-info/top_level.txt