Metadata-Version: 2.1
Name: smoot
Version: 0.1.0
Summary: Surrogate based multi-objective optimization tool
Home-page: https://github.com/OneraHub/smoot
Author: Nathalie Bartoli, Robin Grapin, Rémi Lafage
License: BSD-3
Platform: UNKNOWN
Classifier: Programming Language :: Python :: 3
Classifier: License :: OSI Approved :: BSD License
Classifier: Operating System :: OS Independent
Requires-Python: >=3.6
License-File: LICENSE
